{
    "setImmediate": {
        "prefix": "sim",
        "body": "setImmediate(() => {\n\t${0}\n})"
    },
    "console log": {
        "prefix": "cl",
        "body": "console.log(${0})"
    },
    "forEach loop": {
        "prefix": "fe",
        "body": "${1:iterable}.forEach((${2:item}) => {\n\t${0}\n})"
    },
    "map": {
        "prefix": "map",
        "body": "${1:iterable}.map((${2:item}) => {\n\t${0}\n})"
    },
    "reduce": {
        "prefix": "reduce",
        "body": "${1:iterable}.reduce((${2:previous}, ${3:current}) => {\n\t${0}\n}${4:, initial})"
    },
    "filter": {
        "prefix": "filter",
        "body": "${1:iterable}.filter((${2:item}) => {\n\t${0}\n})"
    },
    "find": {
        "prefix": "find",
        "body": "${1:iterable}.find((${2:item}) => {\n\t${0}\n})"
    },
    "every": {
        "prefix": "every",
        "body": "${1:iterable}.every((${2:item}) => {\n\t${0}\n})"
    },
    "some": {
        "prefix": "some",
        "body": "${1:iterable}.some((${2:item}) => {\n\t${0}\n})"
    }
}
